{"053610.KQ":{"score":70.2,"rank":1},"005930.KS":{"score":68.4,"rank":2},"007070.KS":{"score":67.4,"rank":3},"023530.KS":{"score":64.7,"rank":4},"051360.KQ":{"score":64.5,"rank":5},"282330.KS":{"score":63.9,"rank":6},"012510.KS":{"score":63.2,"rank":7},"329180.KS":{"score":63.1,"rank":8},"036570.KS":{"score":62.7,"rank":9},"011070.KS":{"score":62.6,"rank":10},"402340.KS":{"score":62.2,"rank":11},"003230.KS":{"score":62.0,"rank":12},"032830.KS":{"score":60.8,"rank":13},"278470.KS":{"score":60.7,"rank":14},"004170.KS":{"score":60.6,"rank":15},"000660.KS":{"score":60.2,"rank":16},"021240.KS":{"score":57.9,"rank":17},"069960.KS":{"score":57.7,"rank":18},"008060.KS":{"score":57.6,"rank":19},"267260.KS":{"score":57.2,"rank":20},"131290.KQ":{"score":55.6,"rank":21},"062040.KS":{"score":55.5,"rank":22},"443060.KS":{"score":55.3,"rank":23},"082740.KS":{"score":54.6,"rank":24},"139130.KS":{"score":54.2,"rank":25},"161890.KS":{"score":54.1,"rank":26},"001230.KS":{"score":53.7,"rank":27},"009150.KS":{"score":52.7,"rank":28},"103590.KS":{"score":52.7,"rank":29},"077970.KS":{"score":52.7,"rank":30},"028260.KS":{"score":52.6,"rank":31},"006260.KS":{"score":52.5,"rank":32},"016360.KS":{"score":52.5,"rank":33},"095610.KQ":{"score":51.8,"rank":34},"483650.KS":{"score":51.8,"rank":35},"298040.KS":{"score":50.3,"rank":36},"138930.KS":{"score":50.2,"rank":37},"122990.KQ":{"score":50.0,"rank":38},"001450.KS":{"score":50.0,"rank":39},"322000.KS":{"score":49.9,"rank":40},"005490.KS":{"score":49.7,"rank":41},"025540.KS":{"score":49.6,"rank":42},"195870.KS":{"score":49.4,"rank":43},"192080.KQ":{"score":49.2,"rank":44},"067310.KQ":{"score":49.1,"rank":45},"004370.KS":{"score":49.1,"rank":46},"271560.KS":{"score":49.1,"rank":47},"017670.KS":{"score":48.7,"rank":48},"003490.KS":{"score":48.1,"rank":49},"105560.KS":{"score":48.0,"rank":50},"229640.KS":{"score":47.9,"rank":51},"136540.KQ":{"score":47.7,"rank":52},"150900.KQ":{"score":47.7,"rank":53},"069260.KS":{"score":47.4,"rank":54},"280360.KS":{"score":47.3,"rank":55},"078150.KQ":{"score":47.2,"rank":56},"166090.KQ":{"score":47.1,"rank":57},"175330.KS":{"score":47.1,"rank":58},"178920.KS":{"score":47.0,"rank":59},"009180.KS":{"score":47.0,"rank":60},"086790.KS":{"score":46.8,"rank":61},"055550.KS":{"score":46.7,"rank":62},"068270.KS":{"score":46.1,"rank":63},"327260.KQ":{"score":46.0,"rank":64},"316140.KS":{"score":45.8,"rank":65},"051910.KS":{"score":45.5,"rank":66},"024110.KS":{"score":45.5,"rank":67},"010120.KS":{"score":45.4,"rank":68},"001500.KS":{"score":45.4,"rank":69},"120110.KS":{"score":45.3,"rank":70},"032640.KS":{"score":45.2,"rank":71},"088350.KS":{"score":45.0,"rank":72},"267250.KS":{"score":45.0,"rank":73},"036540.KQ":{"score":44.8,"rank":74},"005030.KS":{"score":44.8,"rank":75},"218410.KQ":{"score":44.7,"rank":76},"041830.KQ":{"score":44.7,"rank":77},"054940.KQ":{"score":44.7,"rank":78},"056360.KQ":{"score":44.6,"rank":79},"054450.KQ":{"score":44.5,"rank":80},"028050.KS":{"score":44.5,"rank":81},"005290.KQ":{"score":44.4,"rank":82},"066570.KS":{"score":44.4,"rank":83},"114090.KS":{"score":44.4,"rank":84},"017390.KS":{"score":44.4,"rank":85},"000990.KS":{"score":44.3,"rank":86},"375500.KS":{"score":44.3,"rank":87},"011200.KS":{"score":44.2,"rank":88},"034590.KS":{"score":44.1,"rank":89},"014680.KS":{"score":44.0,"rank":90},"017960.KS":{"score":43.9,"rank":91},"005940.KS":{"score":43.8,"rank":92},"009540.KS":{"score":43.6,"rank":93},"010140.KS":{"score":43.6,"rank":94},"006360.KS":{"score":43.6,"rank":95},"030200.KS":{"score":43.5,"rank":96},"307950.KS":{"score":43.5,"rank":97},"138040.KS":{"score":43.5,"rank":98},"104830.KQ":{"score":43.4,"rank":99},"051600.KS":{"score":43.4,"rank":100},"187790.KQ":{"score":43.3,"rank":101},"005880.KS":{"score":43.3,"rank":102},"259630.KQ":{"score":43.3,"rank":103},"185750.KS":{"score":43.2,"rank":104},"012330.KS":{"score":43.2,"rank":105},"001440.KS":{"score":43.1,"rank":106},"000500.KS":{"score":43.0,"rank":107},"008770.KS":{"score":43.0,"rank":108},"058430.KS":{"score":42.9,"rank":109},"170790.KQ":{"score":42.7,"rank":110},"274090.KQ":{"score":42.6,"rank":111},"145020.KQ":{"score":42.6,"rank":112},"259960.KS":{"score":42.6,"rank":113},"032850.KQ":{"score":42.6,"rank":114},"064290.KQ":{"score":42.3,"rank":115},"004020.KS":{"score":42.3,"rank":116},"006400.KS":{"score":42.2,"rank":117},"039130.KS":{"score":42.2,"rank":118},"010780.KS":{"score":42.1,"rank":119},"000720.KS":{"score":41.8,"rank":120},"357780.KQ":{"score":41.7,"rank":121},"004690.KS":{"score":41.6,"rank":122},"462520.KS":{"score":41.5,"rank":123},"005380.KS":{"score":41.4,"rank":124},"456040.KS":{"score":41.2,"rank":125},"234300.KQ":{"score":41.2,"rank":126},"222800.KQ":{"score":41.0,"rank":127},"035250.KS":{"score":40.8,"rank":128},"005810.KS":{"score":40.6,"rank":129},"047040.KS":{"score":40.4,"rank":130},"095340.KQ":{"score":40.3,"rank":131},"084370.KQ":{"score":40.3,"rank":132},"039030.KQ":{"score":39.9,"rank":133},"031980.KQ":{"score":39.8,"rank":134},"000210.KS":{"score":39.8,"rank":135},"080220.KQ":{"score":39.7,"rank":136},"086450.KQ":{"score":39.7,"rank":137},"003830.KS":{"score":39.6,"rank":138},"110990.KQ":{"score":39.5,"rank":139},"036930.KQ":{"score":39.4,"rank":140},"082640.KS":{"score":39.4,"rank":141},"298000.KS":{"score":39.4,"rank":142},"281820.KS":{"score":39.3,"rank":143},"403870.KQ":{"score":39.2,"rank":144},"321370.KQ":{"score":39.2,"rank":145},"051900.KS":{"score":39.2,"rank":146},"000810.KS":{"score":39.2,"rank":147},"033640.KQ":{"score":39.1,"rank":148},"064760.KQ":{"score":39.1,"rank":149},"170920.KQ":{"score":39.1,"rank":150},"079550.KS":{"score":39.1,"rank":151},"098460.KQ":{"score":39.0,"rank":152},"083450.KQ":{"score":39.0,"rank":153},"033100.KQ":{"score":38.9,"rank":154},"007660.KS":{"score":38.8,"rank":155},"389500.KQ":{"score":38.8,"rank":156},"006800.KS":{"score":38.8,"rank":157},"456010.KQ":{"score":38.8,"rank":158},"010060.KS":{"score":38.8,"rank":159},"042700.KS":{"score":38.7,"rank":160},"115500.KQ":{"score":38.7,"rank":161},"042510.KQ":{"score":38.6,"rank":162},"006120.KS":{"score":38.2,"rank":163},"203650.KQ":{"score":37.8,"rank":164},"054050.KQ":{"score":37.8,"rank":165},"010170.KQ":{"score":37.7,"rank":166},"336260.KS":{"score":37.6,"rank":167},"339770.KS":{"score":37.6,"rank":168},"006340.KS":{"score":37.4,"rank":169},"020150.KS":{"score":37.4,"rank":170},"199820.KQ":{"score":37.3,"rank":171},"432720.KQ":{"score":37.2,"rank":172},"069080.KQ":{"score":37.2,"rank":173},"059090.KQ":{"score":37.1,"rank":174},"095660.KQ":{"score":37.1,"rank":175},"012450.KS":{"score":37.0,"rank":176},"018670.KS":{"score":37.0,"rank":177},"065450.KQ":{"score":36.9,"rank":178},"207940.KS":{"score":36.8,"rank":179},"078340.KQ":{"score":36.7,"rank":180},"084730.KQ":{"score":36.6,"rank":181},"488280.KQ":{"score":36.6,"rank":182},"000120.KS":{"score":36.5,"rank":183},"317330.KQ":{"score":36.3,"rank":184},"039840.KQ":{"score":36.3,"rank":185},"396270.KQ":{"score":36.2,"rank":186},"005300.KS":{"score":36.1,"rank":187},"010820.KS":{"score":36.0,"rank":188},"097950.KS":{"score":35.8,"rank":189},"189300.KQ":{"score":35.8,"rank":190},"475150.KS":{"score":35.6,"rank":191},"008350.KS":{"score":35.6,"rank":192},"032620.KQ":{"score":35.6,"rank":193},"066970.KS":{"score":35.3,"rank":194},"002320.KS":{"score":35.2,"rank":195},"034020.KS":{"score":35.1,"rank":196},"112610.KS":{"score":35.0,"rank":197},"052710.KQ":{"score":34.9,"rank":198},"047810.KS":{"score":34.3,"rank":199},"035900.KQ":{"score":34.3,"rank":200},"066310.KQ":{"score":34.3,"rank":201},"272290.KQ":{"score":34.1,"rank":202},"271940.KS":{"score":34.1,"rank":203},"079160.KS":{"score":34.1,"rank":204},"071050.KS":{"score":34.0,"rank":205},"002380.KS":{"score":34.0,"rank":206},"039490.KS":{"score":33.9,"rank":207},"096770.KS":{"score":33.8,"rank":208},"003070.KS":{"score":33.7,"rank":209},"011780.KS":{"score":33.6,"rank":210},"058470.KQ":{"score":33.5,"rank":211},"950170.KQ":{"score":33.0,"rank":212},"475560.KS":{"score":33.0,"rank":213},"005830.KS":{"score":33.0,"rank":214},"405100.KQ":{"score":32.9,"rank":215},"005180.KS":{"score":32.6,"rank":216},"007310.KS":{"score":32.6,"rank":217},"018260.KS":{"score":32.5,"rank":218},"001430.KS":{"score":32.5,"rank":219},"011790.KS":{"score":32.2,"rank":220},"112290.KQ":{"score":32.1,"rank":221},"005870.KS":{"score":32.1,"rank":222},"000270.KS":{"score":32.1,"rank":223},"089030.KQ":{"score":31.9,"rank":224},"128940.KS":{"score":31.9,"rank":225},"090360.KQ":{"score":31.7,"rank":226},"462870.KS":{"score":31.6,"rank":227},"140860.KQ":{"score":31.4,"rank":228},"003540.KS":{"score":30.9,"rank":229},"004560.KS":{"score":30.7,"rank":230},"053800.KQ":{"score":30.4,"rank":231},"003090.KS":{"score":30.4,"rank":232},"056190.KQ":{"score":30.4,"rank":233},"000880.KS":{"score":30.2,"rank":234},"015760.KS":{"score":30.0,"rank":235},"083650.KQ":{"score":30.0,"rank":236},"326030.KS":{"score":30.0,"rank":237},"214150.KQ":{"score":30.0,"rank":238},"041510.KQ":{"score":29.9,"rank":239},"053300.KQ":{"score":29.9,"rank":240},"010130.KS":{"score":29.9,"rank":241},"064960.KS":{"score":29.8,"rank":242},"137400.KQ":{"score":29.7,"rank":243},"373220.KS":{"score":29.6,"rank":244},"069620.KS":{"score":29.5,"rank":245},"102710.KQ":{"score":29.5,"rank":246},"192820.KS":{"score":29.5,"rank":247},"196170.KQ":{"score":29.2,"rank":248},"042660.KS":{"score":29.1,"rank":249},"071970.KS":{"score":29.1,"rank":250},"277810.KQ":{"score":29.1,"rank":251},"168360.KQ":{"score":29.0,"rank":252},"323280.KQ":{"score":29.0,"rank":253},"097230.KS":{"score":28.9,"rank":254},"263720.KQ":{"score":28.9,"rank":255},"108490.KQ":{"score":28.8,"rank":256},"036460.KS":{"score":28.8,"rank":257},"240810.KQ":{"score":28.7,"rank":258},"437730.KQ":{"score":28.7,"rank":259},"099320.KQ":{"score":28.6,"rank":260},"237880.KQ":{"score":28.6,"rank":261},"108320.KS":{"score":28.5,"rank":262},"241710.KQ":{"score":28.5,"rank":263},"004980.KS":{"score":28.5,"rank":264},"014830.KS":{"score":28.5,"rank":265},"103140.KS":{"score":28.2,"rank":266},"002790.KS":{"score":28.2,"rank":267},"064350.KS":{"score":28.0,"rank":268},"052690.KS":{"score":27.9,"rank":269},"459510.KQ":{"score":27.9,"rank":270},"211270.KQ":{"score":27.8,"rank":271},"357550.KQ":{"score":27.5,"rank":272},"035420.KS":{"score":27.5,"rank":273},"145720.KS":{"score":27.4,"rank":274},"005740.KS":{"score":27.4,"rank":275},"137310.KS":{"score":27.3,"rank":276},"294870.KS":{"score":27.0,"rank":277},"003350.KS":{"score":26.9,"rank":278},"105840.KS":{"score":26.8,"rank":279},"439260.KS":{"score":26.7,"rank":280},"365340.KQ":{"score":26.7,"rank":281},"474170.KQ":{"score":26.7,"rank":282},"067390.KQ":{"score":26.1,"rank":283},"454910.KS":{"score":26.0,"rank":284},"323410.KS":{"score":25.9,"rank":285},"035720.KS":{"score":25.7,"rank":286},"000100.KS":{"score":25.7,"rank":287},"086900.KQ":{"score":25.7,"rank":288},"014820.KS":{"score":25.4,"rank":289},"008930.KS":{"score":25.3,"rank":290},"122870.KQ":{"score":25.2,"rank":291},"253450.KQ":{"score":25.2,"rank":292},"064550.KQ":{"score":25.1,"rank":293},"035760.KQ":{"score":25.1,"rank":294},"090430.KS":{"score":25.0,"rank":295},"377300.KS":{"score":25.0,"rank":296},"006280.KS":{"score":24.9,"rank":297},"086520.KQ":{"score":24.6,"rank":298},"058610.KQ":{"score":24.6,"rank":299},"123690.KS":{"score":24.6,"rank":300},"200710.KQ":{"score":24.5,"rank":301},"272210.KS":{"score":24.3,"rank":302},"003670.KS":{"score":24.3,"rank":303},"024060.KQ":{"score":24.3,"rank":304},"376300.KQ":{"score":24.2,"rank":305},"009830.KS":{"score":24.1,"rank":306},"247540.KQ":{"score":24.0,"rank":307},"005070.KS":{"score":24.0,"rank":308},"112040.KQ":{"score":24.0,"rank":309},"304100.KQ":{"score":23.9,"rank":310},"125490.KQ":{"score":23.9,"rank":311},"263750.KQ":{"score":23.8,"rank":312},"004140.KS":{"score":23.7,"rank":313},"060280.KQ":{"score":23.6,"rank":314},"382900.KQ":{"score":23.4,"rank":315},"214370.KQ":{"score":23.4,"rank":316},"377330.KQ":{"score":23.1,"rank":317},"099190.KQ":{"score":23.0,"rank":318},"450080.KS":{"score":22.9,"rank":319},"251270.KS":{"score":22.9,"rank":320},"298380.KQ":{"score":22.8,"rank":321},"022100.KS":{"score":22.6,"rank":322},"009070.KS":{"score":22.6,"rank":323},"042940.KQ":{"score":22.6,"rank":324},"095700.KQ":{"score":22.6,"rank":325},"117730.KQ":{"score":22.6,"rank":326},"361610.KS":{"score":22.4,"rank":327},"087010.KQ":{"score":22.4,"rank":328},"141080.KQ":{"score":22.3,"rank":329},"950140.KS":{"score":22.3,"rank":330},"225570.KQ":{"score":22.2,"rank":331},"302440.KS":{"score":22.1,"rank":332},"035080.KQ":{"score":22.1,"rank":333},"372170.KQ":{"score":22.0,"rank":334},"348340.KQ":{"score":22.0,"rank":335},"293490.KQ":{"score":22.0,"rank":336},"033230.KQ":{"score":21.9,"rank":337},"352480.KQ":{"score":21.8,"rank":338},"278280.KQ":{"score":21.7,"rank":339},"186230.KQ":{"score":21.4,"rank":340},"011170.KS":{"score":21.3,"rank":341},"015020.KS":{"score":21.0,"rank":342},"000490.KS":{"score":21.0,"rank":343},"036810.KQ":{"score":20.9,"rank":344},"004090.KS":{"score":20.8,"rank":345},"108860.KQ":{"score":20.5,"rank":346},"194480.KQ":{"score":20.4,"rank":347},"411080.KQ":{"score":19.9,"rank":348},"377480.KQ":{"score":19.8,"rank":349},"014160.KS":{"score":19.8,"rank":350},"403490.KQ":{"score":19.6,"rank":351},"455900.KQ":{"score":19.5,"rank":352},"228760.KQ":{"score":19.3,"rank":353},"092040.KQ":{"score":19.0,"rank":354},"008730.KS":{"score":18.9,"rank":355},"053030.KQ":{"score":18.6,"rank":356},"352820.KS":{"score":18.5,"rank":357},"338220.KQ":{"score":18.4,"rank":358},"028300.KQ":{"score":18.2,"rank":359},"005420.KS":{"score":17.9,"rank":360},"002710.KS":{"score":16.6,"rank":361},"328130.KQ":{"score":15.9,"rank":362},"121850.KQ":{"score":15.0,"rank":363}}