{"CSCO":{"score":89.9,"rank":1},"CBOE":{"score":88.8,"rank":2},"TXN":{"score":88.6,"rank":3},"GOOGL":{"score":83.3,"rank":4},"ROK":{"score":80.5,"rank":5},"NVDA":{"score":79.8,"rank":6},"CF":{"score":79.2,"rank":7},"TRGP":{"score":78.9,"rank":8},"LNTH":{"score":78.6,"rank":9},"NXPI":{"score":78.3,"rank":10},"CAT":{"score":77.2,"rank":11},"SIMO":{"score":76.8,"rank":12},"AMZN":{"score":76.5,"rank":13},"TSM":{"score":76.5,"rank":14},"STX":{"score":76.4,"rank":15},"HWM":{"score":76.4,"rank":16},"PANW":{"score":75.4,"rank":17},"WDC":{"score":74.1,"rank":18},"MNST":{"score":74.1,"rank":19},"ALL":{"score":74.0,"rank":20},"BEN":{"score":73.7,"rank":21},"EXTR":{"score":73.7,"rank":22},"AVGO":{"score":73.5,"rank":23},"QCOM":{"score":72.9,"rank":24},"TRV":{"score":72.9,"rank":25},"AMAT":{"score":72.3,"rank":26},"CVS":{"score":71.6,"rank":27},"BK":{"score":71.3,"rank":28},"ADI":{"score":71.2,"rank":29},"JBHT":{"score":71.2,"rank":30},"VRT":{"score":70.7,"rank":31},"NUE":{"score":70.7,"rank":32},"PAAS":{"score":70.7,"rank":33},"CSX":{"score":70.5,"rank":34},"DVA":{"score":69.9,"rank":35},"LRCX":{"score":69.7,"rank":36},"CW":{"score":69.4,"rank":37},"PWR":{"score":68.7,"rank":38},"APA":{"score":68.5,"rank":39},"SEE":{"score":68.3,"rank":40},"ZM":{"score":68.2,"rank":41},"MS":{"score":68.2,"rank":42},"MRVL":{"score":67.8,"rank":43},"MPC":{"score":67.5,"rank":44},"EBAY":{"score":67.5,"rank":45},"AFL":{"score":67.3,"rank":46},"LIN":{"score":67.3,"rank":47},"GEV":{"score":67.2,"rank":48},"BIIB":{"score":67.0,"rank":49},"KO":{"score":66.9,"rank":50},"MPWR":{"score":66.8,"rank":51},"CRUS":{"score":66.6,"rank":52},"FTNT":{"score":66.5,"rank":53},"EOG":{"score":66.5,"rank":54},"ADM":{"score":66.5,"rank":55},"TWLO":{"score":66.3,"rank":56},"IRM":{"score":66.1,"rank":57},"NTAP":{"score":66.0,"rank":58},"STLD":{"score":66.0,"rank":59},"WMB":{"score":65.8,"rank":60},"AAPL":{"score":65.7,"rank":61},"FSLR":{"score":65.7,"rank":62},"MOV":{"score":65.1,"rank":63},"DDOG":{"score":64.7,"rank":64},"MFC":{"score":64.7,"rank":65},"ALAB":{"score":64.6,"rank":66},"GS":{"score":64.6,"rank":67},"COST":{"score":64.5,"rank":68},"KMI":{"score":63.9,"rank":69},"FRT":{"score":63.9,"rank":70},"AMD":{"score":63.7,"rank":71},"MU":{"score":63.2,"rank":72},"C":{"score":63.0,"rank":73},"GL":{"score":63.0,"rank":74},"VLO":{"score":62.8,"rank":75},"CGNX":{"score":62.5,"rank":76},"LLY":{"score":62.3,"rank":77},"FR":{"score":62.0,"rank":78},"GNRC":{"score":61.8,"rank":79},"AMG":{"score":61.6,"rank":80},"FCX":{"score":61.5,"rank":81},"OXY":{"score":61.3,"rank":82},"PLD":{"score":60.9,"rank":83},"CTVA":{"score":60.5,"rank":84},"CME":{"score":60.2,"rank":85},"BLK":{"score":60.2,"rank":86},"OSCR":{"score":60.2,"rank":87},"DLR":{"score":60.1,"rank":88},"TROW":{"score":60.1,"rank":89},"UNP":{"score":60.0,"rank":90},"CLS":{"score":59.7,"rank":91},"SBUX":{"score":59.2,"rank":92},"CMC":{"score":59.2,"rank":93},"CIEN":{"score":59.1,"rank":94},"IVZ":{"score":59.0,"rank":95},"XPO":{"score":58.9,"rank":96},"OKE":{"score":58.7,"rank":97},"LEA":{"score":58.6,"rank":98},"APP":{"score":58.5,"rank":99},"BUD":{"score":58.4,"rank":100},"ASML":{"score":58.2,"rank":101},"WPC":{"score":58.2,"rank":102},"F":{"score":58.0,"rank":103},"SPG":{"score":58.0,"rank":104},"RS":{"score":57.9,"rank":105},"LSCC":{"score":57.8,"rank":106},"KLAC":{"score":57.7,"rank":107},"NEE":{"score":57.6,"rank":108},"MKSI":{"score":57.3,"rank":109},"ILMN":{"score":57.3,"rank":110},"CRWD":{"score":57.2,"rank":111},"SQM":{"score":57.1,"rank":112},"DELL":{"score":56.8,"rank":113},"TECK":{"score":56.8,"rank":114},"TSN":{"score":56.7,"rank":115},"ON":{"score":56.5,"rank":116},"KLIC":{"score":56.3,"rank":117},"EQIX":{"score":56.1,"rank":118},"FDX":{"score":55.6,"rank":119},"UNH":{"score":55.3,"rank":120},"NDAQ":{"score":55.0,"rank":121},"LYV":{"score":54.8,"rank":122},"SLF":{"score":54.5,"rank":123},"AMKR":{"score":54.4,"rank":124},"SAIA":{"score":54.3,"rank":125},"MSCI":{"score":54.2,"rank":126},"TTWO":{"score":54.1,"rank":127},"APD":{"score":54.1,"rank":128},"DD":{"score":54.0,"rank":129},"ENTG":{"score":53.5,"rank":130},"SM":{"score":53.5,"rank":131},"AME":{"score":53.1,"rank":132},"RAMP":{"score":52.8,"rank":133},"ORCL":{"score":52.5,"rank":134},"SYF":{"score":52.1,"rank":135},"ROKU":{"score":51.9,"rank":136},"SNDK":{"score":51.8,"rank":137},"KEY":{"score":51.8,"rank":138},"RDDT":{"score":51.6,"rank":139},"ARM":{"score":51.3,"rank":140},"SCCO":{"score":50.9,"rank":141},"FORM":{"score":50.8,"rank":142},"MET":{"score":50.8,"rank":143},"SLAB":{"score":50.7,"rank":144},"COHR":{"score":50.1,"rank":145},"STT":{"score":49.9,"rank":146},"CMI":{"score":49.9,"rank":147},"NBIS":{"score":49.8,"rank":148},"ELV":{"score":49.8,"rank":149},"ALLY":{"score":49.7,"rank":150},"ENPH":{"score":49.7,"rank":151},"ETN":{"score":49.6,"rank":152},"CHRW":{"score":49.6,"rank":153},"ET":{"score":49.5,"rank":154},"BRK-B":{"score":49.4,"rank":155},"XOM":{"score":49.4,"rank":156},"WMT":{"score":49.4,"rank":157},"PAA":{"score":49.3,"rank":158},"GEN":{"score":49.2,"rank":159},"NSC":{"score":49.2,"rank":160},"FANG":{"score":49.2,"rank":161},"PSX":{"score":49.2,"rank":162},"SLB":{"score":49.2,"rank":163},"HOLX":{"score":49.2,"rank":164},"TJX":{"score":49.1,"rank":165},"TT":{"score":49.0,"rank":166},"COP":{"score":49.0,"rank":167},"PEP":{"score":49.0,"rank":168},"EA":{"score":48.9,"rank":169},"DVN":{"score":48.8,"rank":170},"PLUG":{"score":48.8,"rank":171},"QSR":{"score":48.8,"rank":172},"NNN":{"score":48.8,"rank":173},"CL":{"score":48.7,"rank":174},"UWM":{"score":48.7,"rank":175},"WPM":{"score":48.7,"rank":176},"CB":{"score":48.6,"rank":177},"RKLB":{"score":48.6,"rank":178},"FTV":{"score":48.6,"rank":179},"HSY":{"score":48.6,"rank":180},"UDR":{"score":48.6,"rank":181},"ODFL":{"score":48.5,"rank":182},"PR":{"score":48.5,"rank":183},"INCY":{"score":48.5,"rank":184},"ROST":{"score":48.5,"rank":185},"SONY":{"score":48.5,"rank":186},"ESS":{"score":48.5,"rank":187},"OR":{"score":48.5,"rank":188},"V":{"score":48.4,"rank":189},"GILD":{"score":48.4,"rank":190},"TGT":{"score":48.4,"rank":191},"FNV":{"score":48.4,"rank":192},"SEDG":{"score":48.3,"rank":193},"NVS":{"score":48.3,"rank":194},"VRTX":{"score":48.3,"rank":195},"AEM":{"score":48.3,"rank":196},"VC":{"score":48.2,"rank":197},"KIM":{"score":48.2,"rank":198},"D":{"score":48.1,"rank":199},"EQR":{"score":48.0,"rank":200},"FCEL":{"score":47.9,"rank":201},"ETR":{"score":47.9,"rank":202},"NTR":{"score":47.9,"rank":203},"O":{"score":47.9,"rank":204},"BMY":{"score":47.8,"rank":205},"CNC":{"score":47.7,"rank":206},"BG":{"score":47.7,"rank":207},"RGLD":{"score":47.7,"rank":208},"COHU":{"score":47.6,"rank":209},"JNJ":{"score":47.6,"rank":210},"VZ":{"score":47.6,"rank":211},"DIOD":{"score":47.5,"rank":212},"NVTS":{"score":47.4,"rank":213},"MCHP":{"score":47.3,"rank":214},"BITF":{"score":47.3,"rank":215},"QS":{"score":47.3,"rank":216},"ADP":{"score":47.3,"rank":217},"AVB":{"score":47.2,"rank":218},"APO":{"score":47.1,"rank":219},"HIG":{"score":47.1,"rank":220},"CVX":{"score":47.1,"rank":221},"ABNB":{"score":47.1,"rank":222},"TXRH":{"score":47.1,"rank":223},"ADBE":{"score":47.0,"rank":224},"GD":{"score":47.0,"rank":225},"STAG":{"score":47.0,"rank":226},"BXP":{"score":47.0,"rank":227},"UBER":{"score":46.9,"rank":228},"MRK":{"score":46.9,"rank":229},"MDLZ":{"score":46.9,"rank":230},"IMAX":{"score":46.8,"rank":231},"VNO":{"score":46.8,"rank":232},"GSAT":{"score":46.8,"rank":233},"MSFT":{"score":46.7,"rank":234},"EW":{"score":46.7,"rank":235},"CFG":{"score":46.6,"rank":236},"LITE":{"score":46.5,"rank":237},"BAM":{"score":46.5,"rank":238},"REG":{"score":46.5,"rank":239},"SHEN":{"score":46.5,"rank":240},"ICE":{"score":46.4,"rank":241},"CI":{"score":46.3,"rank":242},"NFLX":{"score":46.3,"rank":243},"META":{"score":46.2,"rank":244},"AZN":{"score":46.2,"rank":245},"SJM":{"score":46.2,"rank":246},"AMGN":{"score":46.0,"rank":247},"VICI":{"score":46.0,"rank":248},"ICHR":{"score":45.9,"rank":249},"LYB":{"score":45.9,"rank":250},"ADC":{"score":45.8,"rank":251},"PCTY":{"score":45.6,"rank":252},"RJF":{"score":45.6,"rank":253},"PRU":{"score":45.6,"rank":254},"DOV":{"score":45.6,"rank":255},"AEP":{"score":45.6,"rank":256},"HUBB":{"score":45.5,"rank":257},"LNG":{"score":45.5,"rank":258},"MPLX":{"score":45.5,"rank":259},"PFE":{"score":45.5,"rank":260},"RL":{"score":45.5,"rank":261},"IMVT":{"score":45.4,"rank":262},"INVH":{"score":45.4,"rank":263},"AMT":{"score":45.3,"rank":264},"AMBA":{"score":45.3,"rank":265},"AYI":{"score":45.3,"rank":266},"DE":{"score":45.2,"rank":267},"GSK":{"score":45.2,"rank":268},"AMH":{"score":45.2,"rank":269},"CEVA":{"score":45.1,"rank":270},"HUT":{"score":45.1,"rank":271},"SO":{"score":45.1,"rank":272},"HPE":{"score":45.0,"rank":273},"AKAM":{"score":45.0,"rank":274},"AXP":{"score":45.0,"rank":275},"NVT":{"score":45.0,"rank":276},"SCHW":{"score":44.9,"rank":277},"DUK":{"score":44.9,"rank":278},"ED":{"score":44.9,"rank":279},"CORZ":{"score":44.8,"rank":280},"LUNR":{"score":44.8,"rank":281},"NOC":{"score":44.8,"rank":282},"PH":{"score":44.8,"rank":283},"WEC":{"score":44.8,"rank":284},"HUM":{"score":44.8,"rank":285},"ACLS":{"score":44.7,"rank":286},"SRE":{"score":44.7,"rank":287},"BJ":{"score":44.7,"rank":288},"BURL":{"score":44.7,"rank":289},"SOLS":{"score":44.6,"rank":290},"TOL":{"score":44.6,"rank":291},"BCE":{"score":44.6,"rank":292},"WOLF":{"score":44.4,"rank":293},"QRVO":{"score":44.3,"rank":294},"BA":{"score":44.3,"rank":295},"ROP":{"score":44.3,"rank":296},"VSAT":{"score":44.3,"rank":297},"PNC":{"score":44.2,"rank":298},"RIOT":{"score":44.1,"rank":299},"INTU":{"score":44.0,"rank":300},"RF":{"score":44.0,"rank":301},"BX":{"score":44.0,"rank":302},"LMT":{"score":44.0,"rank":303},"RTX":{"score":44.0,"rank":304},"REGN":{"score":44.0,"rank":305},"UPS":{"score":43.8,"rank":306},"CHD":{"score":43.7,"rank":307},"SPGI":{"score":43.6,"rank":308},"ABBV":{"score":43.6,"rank":309},"STZ":{"score":43.6,"rank":310},"FIS":{"score":43.6,"rank":311},"OKTA":{"score":43.5,"rank":312},"SWKS":{"score":43.5,"rank":313},"MAA":{"score":43.5,"rank":314},"INTC":{"score":43.4,"rank":315},"USB":{"score":43.4,"rank":316},"FIVE":{"score":43.4,"rank":317},"PG":{"score":43.4,"rank":318},"PSTG":{"score":43.3,"rank":319},"UCTT":{"score":43.3,"rank":320},"PGR":{"score":43.3,"rank":321},"TFC":{"score":43.2,"rank":322},"BWXT":{"score":43.2,"rank":323},"IDXX":{"score":43.2,"rank":324},"MCO":{"score":43.1,"rank":325},"NTES":{"score":43.1,"rank":326},"KHC":{"score":42.9,"rank":327},"AA":{"score":42.9,"rank":328},"CHKP":{"score":42.7,"rank":329},"WDAY":{"score":42.6,"rank":330},"HON":{"score":42.6,"rank":331},"MA":{"score":42.5,"rank":332},"HII":{"score":42.4,"rank":333},"BKNG":{"score":42.4,"rank":334},"MKC":{"score":42.4,"rank":335},"SON":{"score":42.4,"rank":336},"APLD":{"score":42.3,"rank":337},"AFRM":{"score":42.3,"rank":338},"PYPL":{"score":42.3,"rank":339},"DIS":{"score":42.3,"rank":340},"DHI":{"score":42.3,"rank":341},"EXLS":{"score":42.3,"rank":342},"S":{"score":42.2,"rank":343},"FDS":{"score":42.2,"rank":344},"AWK":{"score":42.2,"rank":345},"PPL":{"score":42.2,"rank":346},"SNY":{"score":42.2,"rank":347},"BAC":{"score":42.1,"rank":348},"SYK":{"score":42.1,"rank":349},"YUM":{"score":42.1,"rank":350},"IAC":{"score":42.1,"rank":351},"ISRG":{"score":42.0,"rank":352},"CRM":{"score":41.9,"rank":353},"ITW":{"score":41.9,"rank":354},"PHM":{"score":41.9,"rank":355},"T":{"score":41.9,"rank":356},"VEEV":{"score":41.8,"rank":357},"ELS":{"score":41.8,"rank":358},"REXR":{"score":41.7,"rank":359},"CCK":{"score":41.7,"rank":360},"PKG":{"score":41.7,"rank":361},"SITM":{"score":41.6,"rank":362},"MHO":{"score":41.6,"rank":363},"NVR":{"score":41.6,"rank":364},"DOW":{"score":41.6,"rank":365},"MELI":{"score":41.5,"rank":366},"BSX":{"score":41.5,"rank":367},"UHS":{"score":41.5,"rank":368},"DEO":{"score":41.5,"rank":369},"CNK":{"score":41.5,"rank":370},"XEL":{"score":41.4,"rank":371},"SBAC":{"score":41.4,"rank":372},"PPG":{"score":41.4,"rank":373},"BE":{"score":41.3,"rank":374},"GM":{"score":41.3,"rank":375},"CPT":{"score":41.3,"rank":376},"SAIC":{"score":41.1,"rank":377},"BMRN":{"score":41.1,"rank":378},"NTNX":{"score":41.0,"rank":379},"LH":{"score":41.0,"rank":380},"TMUS":{"score":41.0,"rank":381},"IBM":{"score":40.9,"rank":382},"ECL":{"score":40.9,"rank":383},"ZD":{"score":40.8,"rank":384},"EXPE":{"score":40.7,"rank":385},"IONQ":{"score":40.6,"rank":386},"AIG":{"score":40.6,"rank":387},"PAYX":{"score":40.6,"rank":388},"CDW":{"score":40.6,"rank":389},"EQH":{"score":40.5,"rank":390},"LHX":{"score":40.5,"rank":391},"HMC":{"score":40.5,"rank":392},"ULTA":{"score":40.5,"rank":393},"SUI":{"score":40.5,"rank":394},"MSI":{"score":40.4,"rank":395},"JPM":{"score":40.3,"rank":396},"IR":{"score":40.3,"rank":397},"ETSY":{"score":40.3,"rank":398},"PLTK":{"score":40.3,"rank":399},"TXT":{"score":40.2,"rank":400},"EXR":{"score":40.2,"rank":401},"ACN":{"score":40.2,"rank":402},"CSGP":{"score":40.1,"rank":403},"NXT":{"score":40.0,"rank":404},"SHW":{"score":40.0,"rank":405},"QBTS":{"score":39.9,"rank":406},"DOCU":{"score":39.9,"rank":407},"CMCSA":{"score":39.9,"rank":408},"DRI":{"score":39.8,"rank":409},"LPLA":{"score":39.7,"rank":410},"BR":{"score":39.6,"rank":411},"DOCN":{"score":39.5,"rank":412},"LDOS":{"score":39.5,"rank":413},"MMM":{"score":39.5,"rank":414},"RCUS":{"score":39.5,"rank":415},"LAC":{"score":39.4,"rank":416},"BAH":{"score":39.3,"rank":417},"PVH":{"score":39.2,"rank":418},"WULF":{"score":39.1,"rank":419},"ONTO":{"score":39.1,"rank":420},"CCI":{"score":39.0,"rank":421},"TRI":{"score":38.9,"rank":422},"CACI":{"score":38.9,"rank":423},"NVCR":{"score":38.9,"rank":424},"U":{"score":38.8,"rank":425},"KBH":{"score":38.8,"rank":426},"SPOK":{"score":38.8,"rank":427},"CLX":{"score":38.7,"rank":428},"KR":{"score":38.6,"rank":429},"MOH":{"score":38.4,"rank":430},"CBRE":{"score":38.4,"rank":431},"ATR":{"score":38.3,"rank":432},"EFX":{"score":38.2,"rank":433},"DHR":{"score":38.1,"rank":434},"ALB":{"score":38.1,"rank":435},"VRNS":{"score":38.0,"rank":436},"CRCL":{"score":37.9,"rank":437},"FLNC":{"score":37.9,"rank":438},"COR":{"score":37.9,"rank":439},"CLSK":{"score":37.8,"rank":440},"CARR":{"score":37.8,"rank":441},"DAL":{"score":37.8,"rank":442},"HCA":{"score":37.8,"rank":443},"EXC":{"score":37.7,"rank":444},"NTLA":{"score":37.7,"rank":445},"RGTI":{"score":37.6,"rank":446},"ZBH":{"score":37.6,"rank":447},"HD":{"score":37.5,"rank":448},"IREN":{"score":37.4,"rank":449},"BALL":{"score":37.4,"rank":450},"OTIS":{"score":37.3,"rank":451},"MP":{"score":37.3,"rank":452},"WFC":{"score":37.1,"rank":453},"LEN":{"score":37.1,"rank":454},"GPN":{"score":37.0,"rank":455},"BWX":{"score":37.0,"rank":456},"KMB":{"score":37.0,"rank":457},"PINS":{"score":37.0,"rank":458},"TSCO":{"score":36.9,"rank":459},"PUBM":{"score":36.7,"rank":460},"MCD":{"score":36.6,"rank":461},"NIO":{"score":36.5,"rank":462},"CIFR":{"score":36.3,"rank":463},"TDG":{"score":36.3,"rank":464},"GIS":{"score":36.3,"rank":465},"MTH":{"score":36.3,"rank":466},"TMO":{"score":36.2,"rank":467},"LI":{"score":36.1,"rank":468},"MARA":{"score":36.0,"rank":469},"VRSK":{"score":36.0,"rank":470},"MDT":{"score":35.8,"rank":471},"ABT":{"score":35.7,"rank":472},"MCK":{"score":35.6,"rank":473},"EMN":{"score":35.3,"rank":474},"MGNI":{"score":35.2,"rank":475},"TENB":{"score":35.1,"rank":476},"CPB":{"score":35.1,"rank":477},"MOS":{"score":35.1,"rank":478},"BOX":{"score":35.0,"rank":479},"BTDR":{"score":35.0,"rank":480},"CAVA":{"score":35.0,"rank":481},"CRWV":{"score":34.9,"rank":482},"DKNG":{"score":34.9,"rank":483},"CC":{"score":34.8,"rank":484},"CGON":{"score":34.7,"rank":485},"COF":{"score":34.5,"rank":486},"TAP":{"score":34.5,"rank":487},"TU":{"score":34.5,"rank":488},"APTV":{"score":34.4,"rank":489},"CMG":{"score":34.3,"rank":490},"OLN":{"score":34.3,"rank":491},"RBRK":{"score":34.2,"rank":492},"COIN":{"score":34.0,"rank":493},"KGC":{"score":34.0,"rank":494},"CCJ":{"score":33.9,"rank":495},"AU":{"score":33.9,"rank":496},"GFI":{"score":33.9,"rank":497},"NEM":{"score":33.9,"rank":498},"NVO":{"score":33.8,"rank":499},"CAG":{"score":33.8,"rank":500},"ONON":{"score":33.6,"rank":501},"TPR":{"score":33.5,"rank":502},"UAL":{"score":33.4,"rank":503},"SAM":{"score":33.4,"rank":504},"TEAM":{"score":33.3,"rank":505},"ANET":{"score":33.3,"rank":506},"THC":{"score":33.2,"rank":507},"BTBT":{"score":33.1,"rank":508},"TM":{"score":33.0,"rank":509},"DXCM":{"score":32.9,"rank":510},"OWL":{"score":32.8,"rank":511},"CFLT":{"score":32.6,"rank":512},"NKE":{"score":32.6,"rank":513},"QLYS":{"score":32.4,"rank":514},"DPZ":{"score":32.3,"rank":515},"IP":{"score":32.2,"rank":516},"MSTR":{"score":31.9,"rank":517},"SNAP":{"score":31.8,"rank":518},"CE":{"score":31.8,"rank":519},"SOUN":{"score":31.7,"rank":520},"LOW":{"score":31.3,"rank":521},"HOOD":{"score":31.0,"rank":522},"PATH":{"score":30.8,"rank":523},"TSLA":{"score":30.7,"rank":524},"SPOT":{"score":30.6,"rank":525},"TOST":{"score":30.5,"rank":526},"ALGN":{"score":30.5,"rank":527},"EDIT":{"score":30.4,"rank":528},"DV":{"score":30.4,"rank":529},"CEG":{"score":30.3,"rank":530},"RPD":{"score":30.2,"rank":531},"NU":{"score":30.2,"rank":532},"TERN":{"score":30.2,"rank":533},"PDD":{"score":30.2,"rank":534},"ARES":{"score":30.0,"rank":535},"MRNA":{"score":30.0,"rank":536},"ALNY":{"score":29.7,"rank":537},"DG":{"score":29.7,"rank":538},"SE":{"score":29.6,"rank":539},"SOFI":{"score":29.6,"rank":540},"WEX":{"score":29.6,"rank":541},"CVCO":{"score":29.5,"rank":542},"ZS":{"score":29.4,"rank":543},"LULU":{"score":29.4,"rank":544},"AG":{"score":29.2,"rank":545},"HL":{"score":29.1,"rank":546},"NOW":{"score":29.0,"rank":547},"JOBY":{"score":28.9,"rank":548},"TROX":{"score":28.9,"rank":549},"VFC":{"score":28.7,"rank":550},"SMG":{"score":28.7,"rank":551},"SMCI":{"score":28.6,"rank":552},"CRTO":{"score":28.6,"rank":553},"WBD":{"score":28.6,"rank":554},"OKLO":{"score":28.5,"rank":555},"PLTR":{"score":28.4,"rank":556},"DLTR":{"score":28.4,"rank":557},"GOLD":{"score":28.4,"rank":558},"MDB":{"score":28.2,"rank":559},"CHTR":{"score":28.2,"rank":560},"HUBS":{"score":28.0,"rank":561},"BEAM":{"score":27.9,"rank":562},"DUOL":{"score":27.7,"rank":563},"AXON":{"score":27.7,"rank":564},"NET":{"score":27.6,"rank":565},"SHOP":{"score":27.4,"rank":566},"BBAI":{"score":27.3,"rank":567},"ESTC":{"score":26.9,"rank":568},"KTOS":{"score":26.6,"rank":569},"SKY":{"score":26.5,"rank":570},"OLLI":{"score":26.1,"rank":571},"RKT":{"score":26.1,"rank":572},"CPNG":{"score":25.9,"rank":573},"MNDY":{"score":25.8,"rank":574},"WK":{"score":25.8,"rank":575},"SNOW":{"score":25.7,"rank":576},"KKR":{"score":25.6,"rank":577},"LUV":{"score":25.6,"rank":578},"TLN":{"score":25.2,"rank":579},"ASTS":{"score":25.1,"rank":580},"CALX":{"score":25.1,"rank":581},"GTLB":{"score":25.0,"rank":582},"AAL":{"score":25.0,"rank":583},"NNE":{"score":24.9,"rank":584},"WING":{"score":24.6,"rank":585},"EL":{"score":24.3,"rank":586},"RUN":{"score":24.2,"rank":587},"CRSP":{"score":24.2,"rank":588},"HIMS":{"score":24.2,"rank":589},"TTD":{"score":24.1,"rank":590},"KYMR":{"score":23.9,"rank":591},"STLA":{"score":23.9,"rank":592},"CLF":{"score":23.8,"rank":593},"CELH":{"score":23.6,"rank":594},"UEC":{"score":23.4,"rank":595},"VST":{"score":23.4,"rank":596},"ARVN":{"score":22.9,"rank":597},"MAN":{"score":22.9,"rank":598},"BNTX":{"score":22.8,"rank":599},"BILL":{"score":22.6,"rank":600},"AZTA":{"score":22.6,"rank":601},"FISV":{"score":22.6,"rank":602},"FOUR":{"score":22.4,"rank":603},"UUUU":{"score":22.4,"rank":604},"ARRY":{"score":22.0,"rank":605},"GPCR":{"score":21.9,"rank":606},"CG":{"score":21.6,"rank":607},"DNN":{"score":21.5,"rank":608},"PEPG":{"score":20.9,"rank":609},"LBRDK":{"score":20.9,"rank":610},"ACHR":{"score":20.8,"rank":611},"AEO":{"score":20.8,"rank":612},"STEM":{"score":20.4,"rank":613},"W":{"score":20.4,"rank":614},"SMR":{"score":20.2,"rank":615},"VKTX":{"score":20.2,"rank":616},"XPEV":{"score":20.0,"rank":617},"UPST":{"score":19.8,"rank":618},"ENVX":{"score":19.7,"rank":619},"NRG":{"score":19.4,"rank":620},"SHAK":{"score":19.3,"rank":621},"ALT":{"score":18.3,"rank":622},"AMC":{"score":18.1,"rank":623},"AI":{"score":17.7,"rank":624},"CPRI":{"score":17.4,"rank":625},"TEM":{"score":17.1,"rank":626},"FMC":{"score":17.0,"rank":627},"FUBO":{"score":16.9,"rank":628},"RIVN":{"score":16.8,"rank":629},"LCID":{"score":16.4,"rank":630},"RBLX":{"score":15.2,"rank":631}}